[
 {
  "id": "player_sheffield_wednesday_0001",
  "nome": "Marvelous Nakamba",
  "idade": 32,
  "nacionalidade": "Zimbabwe",
  "posicaoPrincipal": "VOL",
  "posicoesSecundarias": [],
  "pernaDominante": "D",
  "atributos": {
   "finalizacao": 54,
   "passe": 75,
   "marcacao": 83,
   "desarme": 78,
   "velocidade": 68,
   "resistencia": 73,
   "forca": 77,
   "reflexos": 12,
   "posicionamento": 71,
   "drible": 61,
   "cabeceio": 68,
   "cruzamento": 73
  },
  "overall": 70,
  "potencial": 70,
  "condicaoFisica": 100,
  "moral": 70,
  "forma": 0,
  "valorMercado": 290000,
  "salario": 27000,
  "contratoAte": "2028-12-31",
  "clubeId": "club_sheffield_wednesday",
  "lesionado": false,
  "diasLesao": 0,
  "suspenso": false,
  "jogosSuspensao": 0,
  "estatisticasTemporada": {
   "temporada": "2026",
   "jogos": 0,
   "gols": 0,
   "assistencias": 0,
   "cartoesAmarelos": 0,
   "cartoesVermelhos": 0,
   "notaMedia": 0
  },
  "historicoTemporadas": []
 },
 {
  "id": "player_sheffield_wednesday_0002",
  "nome": "Max Lowe",
  "idade": 29,
  "nacionalidade": "England",
  "posicaoPrincipal": "LE",
  "posicoesSecundarias": [],
  "pernaDominante": "D",
  "atributos": {
   "finalizacao": 54,
   "passe": 70,
   "marcacao": 76,
   "desarme": 74,
   "velocidade": 79,
   "resistencia": 79,
   "forca": 62,
   "reflexos": 14,
   "posicionamento": 70,
   "drible": 70,
   "cabeceio": 61,
   "cruzamento": 82
  },
  "overall": 70,
  "potencial": 70,
  "condicaoFisica": 100,
  "moral": 70,
  "forma": 0,
  "valorMercado": 410000,
  "salario": 30000,
  "contratoAte": "2028-12-31",
  "clubeId": "club_sheffield_wednesday",
  "lesionado": false,
  "diasLesao": 0,
  "suspenso": false,
  "jogosSuspensao": 0,
  "estatisticasTemporada": {
   "temporada": "2026",
   "jogos": 0,
   "gols": 0,
   "assistencias": 0,
   "cartoesAmarelos": 0,
   "cartoesVermelhos": 0,
   "notaMedia": 0
  },
  "historicoTemporadas": []
 },
 {
  "id": "player_sheffield_wednesday_0003",
  "nome": "Jamal Lowe",
  "idade": 31,
  "nacionalidade": "Jamaica",
  "posicaoPrincipal": "CA",
  "posicoesSecundarias": [],
  "pernaDominante": "D",
  "atributos": {
   "finalizacao": 85,
   "passe": 63,
   "marcacao": 43,
   "desarme": 46,
   "velocidade": 72,
   "resistencia": 70,
   "forca": 78,
   "reflexos": 15,
   "posicionamento": 79,
   "drible": 73,
   "cabeceio": 75,
   "cruzamento": 62
  },
  "overall": 70,
  "potencial": 70,
  "condicaoFisica": 100,
  "moral": 70,
  "forma": 0,
  "valorMercado": 290000,
  "salario": 27000,
  "contratoAte": "2028-12-31",
  "clubeId": "club_sheffield_wednesday",
  "lesionado": false,
  "diasLesao": 0,
  "suspenso": false,
  "jogosSuspensao": 0,
  "estatisticasTemporada": {
   "temporada": "2026",
   "jogos": 0,
   "gols": 0,
   "assistencias": 0,
   "cartoesAmarelos": 0,
   "cartoesVermelhos": 0,
   "notaMedia": 0
  },
  "historicoTemporadas": []
 },
 {
  "id": "player_sheffield_wednesday_0004",
  "nome": "Nathaniel Chalobah",
  "idade": 31,
  "nacionalidade": "England",
  "posicaoPrincipal": "VOL",
  "posicoesSecundarias": [],
  "pernaDominante": "D",
  "atributos": {
   "finalizacao": 56,
   "passe": 72,
   "marcacao": 78,
   "desarme": 76,
   "velocidade": 64,
   "resistencia": 77,
   "forca": 71,
   "reflexos": 14,
   "posicionamento": 72,
   "drible": 63,
   "cabeceio": 65,
   "cruzamento": 68
  },
  "overall": 69,
  "potencial": 69,
  "condicaoFisica": 100,
  "moral": 70,
  "forma": 0,
  "valorMercado": 250000,
  "salario": 26000,
  "contratoAte": "2028-12-31",
  "clubeId": "club_sheffield_wednesday",
  "lesionado": false,
  "diasLesao": 0,
  "suspenso": false,
  "jogosSuspensao": 0,
  "estatisticasTemporada": {
   "temporada": "2026",
   "jogos": 0,
   "gols": 0,
   "assistencias": 0,
   "cartoesAmarelos": 0,
   "cartoesVermelhos": 0,
   "notaMedia": 0
  },
  "historicoTemporadas": []
 },
 {
  "id": "player_sheffield_wednesday_0005",
  "nome": "Di'Shon Bernard",
  "idade": 25,
  "nacionalidade": "Jamaica",
  "posicaoPrincipal": "ZAG",
  "posicoesSecundarias": [],
  "pernaDominante": "D",
  "atributos": {
   "finalizacao": 44,
   "passe": 63,
   "marcacao": 84,
   "desarme": 78,
   "velocidade": 60,
   "resistencia": 71,
   "forca": 80,
   "reflexos": 17,
   "posicionamento": 73,
   "drible": 52,
   "cabeceio": 77,
   "cruzamento": 51
  },
  "overall": 69,
  "potencial": 69,
  "condicaoFisica": 100,
  "moral": 70,
  "forma": 0,
  "valorMercado": 410000,
  "salario": 30000,
  "contratoAte": "2028-12-31",
  "clubeId": "club_sheffield_wednesday",
  "lesionado": false,
  "diasLesao": 0,
  "suspenso": false,
  "jogosSuspensao": 0,
  "estatisticasTemporada": {
   "temporada": "2026",
   "jogos": 0,
   "gols": 0,
   "assistencias": 0,
   "cartoesAmarelos": 0,
   "cartoesVermelhos": 0,
   "notaMedia": 0
  },
  "historicoTemporadas": []
 },
 {
  "id": "player_sheffield_wednesday_0006",
  "nome": "Svante Ingelsson",
  "idade": 28,
  "nacionalidade": "Sweden",
  "posicaoPrincipal": "MC",
  "posicoesSecundarias": [],
  "pernaDominante": "D",
  "atributos": {
   "finalizacao": 65,
   "passe": 79,
   "marcacao": 69,
   "desarme": 66,
   "velocidade": 67,
   "resistencia": 78,
   "forca": 63,
   "reflexos": 15,
   "posicionamento": 68,
   "drible": 72,
   "cabeceio": 58,
   "cruzamento": 71
  },
  "overall": 69,
  "potencial": 69,
  "condicaoFisica": 100,
  "moral": 70,
  "forma": 0,
  "valorMercado": 350000,
  "salario": 29000,
  "contratoAte": "2028-12-31",
  "clubeId": "club_sheffield_wednesday",
  "lesionado": false,
  "diasLesao": 0,
  "suspenso": false,
  "jogosSuspensao": 0,
  "estatisticasTemporada": {
   "temporada": "2026",
   "jogos": 0,
   "gols": 0,
   "assistencias": 0,
   "cartoesAmarelos": 0,
   "cartoesVermelhos": 0,
   "notaMedia": 0
  },
  "historicoTemporadas": []
 },
 {
  "id": "player_sheffield_wednesday_0007",
  "nome": "Dominic Iorfa",
  "idade": 31,
  "nacionalidade": "England",
  "posicaoPrincipal": "ZAG",
  "posicoesSecundarias": [],
  "pernaDominante": "D",
  "atributos": {
   "finalizacao": 43,
   "passe": 65,
   "marcacao": 83,
   "desarme": 75,
   "velocidade": 59,
   "resistencia": 67,
   "forca": 81,
   "reflexos": 11,
   "posicionamento": 70,
   "drible": 49,
   "cabeceio": 74,
   "cruzamento": 54
  },
  "overall": 68,
  "potencial": 68,
  "condicaoFisica": 100,
  "moral": 70,
  "forma": 0,
  "valorMercado": 220000,
  "salario": 26000,
  "contratoAte": "2028-12-31",
  "clubeId": "club_sheffield_wednesday",
  "lesionado": false,
  "diasLesao": 0,
  "suspenso": false,
  "jogosSuspensao": 0,
  "estatisticasTemporada": {
   "temporada": "2026",
   "jogos": 0,
   "gols": 0,
   "assistencias": 0,
   "cartoesAmarelos": 0,
   "cartoesVermelhos": 0,
   "notaMedia": 0
  },
  "historicoTemporadas": []
 },
 {
  "id": "player_sheffield_wednesday_0008",
  "nome": "Jerry Yates",
  "idade": 29,
  "nacionalidade": "England",
  "posicaoPrincipal": "CA",
  "posicoesSecundarias": [],
  "pernaDominante": "D",
  "atributos": {
   "finalizacao": 82,
   "passe": 56,
   "marcacao": 40,
   "desarme": 45,
   "velocidade": 75,
   "resistencia": 65,
   "forca": 73,
   "reflexos": 12,
   "posicionamento": 72,
   "drible": 69,
   "cabeceio": 74,
   "cruzamento": 58
  },
  "overall": 67,
  "potencial": 67,
  "condicaoFisica": 100,
  "moral": 70,
  "forma": 0,
  "valorMercado": 270000,
  "salario": 27000,
  "contratoAte": "2028-12-31",
  "clubeId": "club_sheffield_wednesday",
  "lesionado": false,
  "diasLesao": 0,
  "suspenso": false,
  "jogosSuspensao": 0,
  "estatisticasTemporada": {
   "temporada": "2026",
   "jogos": 0,
   "gols": 0,
   "assistencias": 0,
   "cartoesAmarelos": 0,
   "cartoesVermelhos": 0,
   "notaMedia": 0
  },
  "historicoTemporadas": []
 },
 {
  "id": "player_sheffield_wednesday_0009",
  "nome": "Iké Ugbo",
  "idade": 27,
  "nacionalidade": "Canada",
  "posicaoPrincipal": "CA",
  "posicoesSecundarias": [],
  "pernaDominante": "D",
  "atributos": {
   "finalizacao": 77,
   "passe": 56,
   "marcacao": 39,
   "desarme": 44,
   "velocidade": 73,
   "resistencia": 64,
   "forca": 74,
   "reflexos": 10,
   "posicionamento": 72,
   "drible": 64,
   "cabeceio": 74,
   "cruzamento": 60
  },
  "overall": 67,
  "potencial": 67,
  "condicaoFisica": 100,
  "moral": 70,
  "forma": 0,
  "valorMercado": 310000,
  "salario": 28000,
  "contratoAte": "2028-12-31",
  "clubeId": "club_sheffield_wednesday",
  "lesionado": false,
  "diasLesao": 0,
  "suspenso": false,
  "jogosSuspensao": 0,
  "estatisticasTemporada": {
   "temporada": "2026",
   "jogos": 0,
   "gols": 0,
   "assistencias": 0,
   "cartoesAmarelos": 0,
   "cartoesVermelhos": 0,
   "notaMedia": 0
  },
  "historicoTemporadas": []
 },
 {
  "id": "player_sheffield_wednesday_0010",
  "nome": "Liam Palmer",
  "idade": 34,
  "nacionalidade": "Scotland",
  "posicaoPrincipal": "ZAG",
  "posicoesSecundarias": [],
  "pernaDominante": "D",
  "atributos": {
   "finalizacao": 42,
   "passe": 66,
   "marcacao": 80,
   "desarme": 76,
   "velocidade": 62,
   "resistencia": 69,
   "forca": 78,
   "reflexos": 11,
   "posicionamento": 69,
   "drible": 50,
   "cabeceio": 78,
   "cruzamento": 55
  },
  "overall": 67,
  "potencial": 67,
  "condicaoFisica": 100,
  "moral": 70,
  "forma": 0,
  "valorMercado": 120000,
  "salario": 23000,
  "contratoAte": "2028-12-31",
  "clubeId": "club_sheffield_wednesday",
  "lesionado": false,
  "diasLesao": 0,
  "suspenso": false,
  "jogosSuspensao": 0,
  "estatisticasTemporada": {
   "temporada": "2026",
   "jogos": 0,
   "gols": 0,
   "assistencias": 0,
   "cartoesAmarelos": 0,
   "cartoesVermelhos": 0,
   "notaMedia": 0
  },
  "historicoTemporadas": []
 },
 {
  "id": "player_sheffield_wednesday_0011",
  "nome": "Pierce Charles",
  "idade": 20,
  "nacionalidade": "Northern Ireland",
  "posicaoPrincipal": "GOL",
  "posicoesSecundarias": [],
  "pernaDominante": "D",
  "atributos": {
   "finalizacao": 12,
   "passe": 49,
   "marcacao": 20,
   "desarme": 16,
   "velocidade": 39,
   "resistencia": 57,
   "forca": 66,
   "reflexos": 82,
   "posicionamento": 76,
   "drible": 24,
   "cabeceio": 20,
   "cruzamento": 18
  },
  "overall": 67,
  "potencial": 71,
  "condicaoFisica": 100,
  "moral": 70,
  "forma": 0,
  "valorMercado": 330000,
  "salario": 28000,
  "contratoAte": "2028-12-31",
  "clubeId": "club_sheffield_wednesday",
  "lesionado": false,
  "diasLesao": 0,
  "suspenso": false,
  "jogosSuspensao": 0,
  "estatisticasTemporada": {
   "temporada": "2026",
   "jogos": 0,
   "gols": 0,
   "assistencias": 0,
   "cartoesAmarelos": 0,
   "cartoesVermelhos": 0,
   "notaMedia": 0
  },
  "historicoTemporadas": []
 },
 {
  "id": "player_sheffield_wednesday_0012",
  "nome": "Joel Ndala",
  "idade": 20,
  "nacionalidade": "England",
  "posicaoPrincipal": "PE",
  "posicoesSecundarias": [],
  "pernaDominante": "D",
  "atributos": {
   "finalizacao": 70,
   "passe": 66,
   "marcacao": 47,
   "desarme": 45,
   "velocidade": 75,
   "resistencia": 68,
   "forca": 59,
   "reflexos": 11,
   "posicionamento": 69,
   "drible": 75,
   "cabeceio": 61,
   "cruzamento": 72
  },
  "overall": 66,
  "potencial": 75,
  "condicaoFisica": 100,
  "moral": 70,
  "forma": 0,
  "valorMercado": 290000,
  "salario": 27000,
  "contratoAte": "2028-12-31",
  "clubeId": "club_sheffield_wednesday",
  "lesionado": false,
  "diasLesao": 0,
  "suspenso": false,
  "jogosSuspensao": 0,
  "estatisticasTemporada": {
   "temporada": "2026",
   "jogos": 0,
   "gols": 0,
   "assistencias": 0,
   "cartoesAmarelos": 0,
   "cartoesVermelhos": 0,
   "notaMedia": 0
  },
  "historicoTemporadas": []
 },
 {
  "id": "player_sheffield_wednesday_0013",
  "nome": "Olaf Kobacki",
  "idade": 25,
  "nacionalidade": "Poland",
  "posicaoPrincipal": "PE",
  "posicoesSecundarias": [],
  "pernaDominante": "D",
  "atributos": {
   "finalizacao": 68,
   "passe": 65,
   "marcacao": 49,
   "desarme": 44,
   "velocidade": 75,
   "resistencia": 63,
   "forca": 54,
   "reflexos": 7,
   "posicionamento": 63,
   "drible": 74,
   "cabeceio": 56,
   "cruzamento": 74
  },
  "overall": 65,
  "potencial": 65,
  "condicaoFisica": 100,
  "moral": 70,
  "forma": 0,
  "valorMercado": 230000,
  "salario": 26000,
  "contratoAte": "2028-12-31",
  "clubeId": "club_sheffield_wednesday",
  "lesionado": false,
  "diasLesao": 0,
  "suspenso": false,
  "jogosSuspensao": 0,
  "estatisticasTemporada": {
   "temporada": "2026",
   "jogos": 0,
   "gols": 0,
   "assistencias": 0,
   "cartoesAmarelos": 0,
   "cartoesVermelhos": 0,
   "notaMedia": 0
  },
  "historicoTemporadas": []
 },
 {
  "id": "player_sheffield_wednesday_0014",
  "nome": "Tayo Adaramola",
  "idade": 22,
  "nacionalidade": "Republic of Ireland",
  "posicaoPrincipal": "LE",
  "posicoesSecundarias": [],
  "pernaDominante": "D",
  "atributos": {
   "finalizacao": 47,
   "passe": 68,
   "marcacao": 70,
   "desarme": 72,
   "velocidade": 75,
   "resistencia": 70,
   "forca": 57,
   "reflexos": 11,
   "posicionamento": 59,
   "drible": 69,
   "cabeceio": 53,
   "cruzamento": 75
  },
  "overall": 65,
  "potencial": 69,
  "condicaoFisica": 100,
  "moral": 70,
  "forma": 0,
  "valorMercado": 230000,
  "salario": 26000,
  "contratoAte": "2028-12-31",
  "clubeId": "club_sheffield_wednesday",
  "lesionado": false,
  "diasLesao": 0,
  "suspenso": false,
  "jogosSuspensao": 0,
  "estatisticasTemporada": {
   "temporada": "2026",
   "jogos": 0,
   "gols": 0,
   "assistencias": 0,
   "cartoesAmarelos": 0,
   "cartoesVermelhos": 0,
   "notaMedia": 0
  },
  "historicoTemporadas": []
 },
 {
  "id": "player_sheffield_wednesday_0015",
  "nome": "Gabriel Otegbayo",
  "idade": 21,
  "nacionalidade": "Republic of Ireland",
  "posicaoPrincipal": "ZAG",
  "posicoesSecundarias": [],
  "pernaDominante": "D",
  "atributos": {
   "finalizacao": 39,
   "passe": 62,
   "marcacao": 78,
   "desarme": 72,
   "velocidade": 57,
   "resistencia": 67,
   "forca": 77,
   "reflexos": 9,
   "posicionamento": 70,
   "drible": 48,
   "cabeceio": 75,
   "cruzamento": 53
  },
  "overall": 65,
  "potencial": 66,
  "condicaoFisica": 100,
  "moral": 70,
  "forma": 0,
  "valorMercado": 250000,
  "salario": 26000,
  "contratoAte": "2028-12-31",
  "clubeId": "club_sheffield_wednesday",
  "lesionado": false,
  "diasLesao": 0,
  "suspenso": false,
  "jogosSuspensao": 0,
  "estatisticasTemporada": {
   "temporada": "2026",
   "jogos": 0,
   "gols": 0,
   "assistencias": 0,
   "cartoesAmarelos": 0,
   "cartoesVermelhos": 0,
   "notaMedia": 0
  },
  "historicoTemporadas": []
 },
 {
  "id": "player_sheffield_wednesday_0016",
  "nome": "Murphy Cooper",
  "idade": 24,
  "nacionalidade": "England",
  "posicaoPrincipal": "GOL",
  "posicoesSecundarias": [],
  "pernaDominante": "D",
  "atributos": {
   "finalizacao": 12,
   "passe": 51,
   "marcacao": 15,
   "desarme": 17,
   "velocidade": 32,
   "resistencia": 59,
   "forca": 63,
   "reflexos": 77,
   "posicionamento": 75,
   "drible": 17,
   "cabeceio": 17,
   "cruzamento": 14
  },
  "overall": 64,
  "potencial": 64,
  "condicaoFisica": 100,
  "moral": 70,
  "forma": 0,
  "valorMercado": 200000,
  "salario": 25000,
  "contratoAte": "2028-12-31",
  "clubeId": "club_sheffield_wednesday",
  "lesionado": false,
  "diasLesao": 0,
  "suspenso": false,
  "jogosSuspensao": 0,
  "estatisticasTemporada": {
   "temporada": "2026",
   "jogos": 0,
   "gols": 0,
   "assistencias": 0,
   "cartoesAmarelos": 0,
   "cartoesVermelhos": 0,
   "notaMedia": 0
  },
  "historicoTemporadas": []
 },
 {
  "id": "player_sheffield_wednesday_0017",
  "nome": "Charlie McNeill",
  "idade": 22,
  "nacionalidade": "England",
  "posicaoPrincipal": "CA",
  "posicoesSecundarias": [],
  "pernaDominante": "D",
  "atributos": {
   "finalizacao": 75,
   "passe": 56,
   "marcacao": 36,
   "desarme": 37,
   "velocidade": 72,
   "resistencia": 63,
   "forca": 70,
   "reflexos": 11,
   "posicionamento": 69,
   "drible": 66,
   "cabeceio": 75,
   "cruzamento": 57
  },
  "overall": 64,
  "potencial": 67,
  "condicaoFisica": 100,
  "moral": 70,
  "forma": 0,
  "valorMercado": 200000,
  "salario": 25000,
  "contratoAte": "2028-12-31",
  "clubeId": "club_sheffield_wednesday",
  "lesionado": false,
  "diasLesao": 0,
  "suspenso": false,
  "jogosSuspensao": 0,
  "estatisticasTemporada": {
   "temporada": "2026",
   "jogos": 0,
   "gols": 0,
   "assistencias": 0,
   "cartoesAmarelos": 0,
   "cartoesVermelhos": 0,
   "notaMedia": 0
  },
  "historicoTemporadas": []
 },
 {
  "id": "player_sheffield_wednesday_0018",
  "nome": "Sean Fusire",
  "idade": 21,
  "nacionalidade": "Zimbabwe",
  "posicaoPrincipal": "MC",
  "posicoesSecundarias": [],
  "pernaDominante": "D",
  "atributos": {
   "finalizacao": 55,
   "passe": 71,
   "marcacao": 63,
   "desarme": 65,
   "velocidade": 59,
   "resistencia": 71,
   "forca": 60,
   "reflexos": 7,
   "posicionamento": 59,
   "drible": 65,
   "cabeceio": 54,
   "cruzamento": 65
  },
  "overall": 62,
  "potencial": 66,
  "condicaoFisica": 100,
  "moral": 70,
  "forma": 0,
  "valorMercado": 170000,
  "salario": 24000,
  "contratoAte": "2028-12-31",
  "clubeId": "club_sheffield_wednesday",
  "lesionado": false,
  "diasLesao": 0,
  "suspenso": false,
  "jogosSuspensao": 0,
  "estatisticasTemporada": {
   "temporada": "2026",
   "jogos": 0,
   "gols": 0,
   "assistencias": 0,
   "cartoesAmarelos": 0,
   "cartoesVermelhos": 0,
   "notaMedia": 0
  },
  "historicoTemporadas": []
 },
 {
  "id": "player_sheffield_wednesday_0019",
  "nome": "Rio Shipston",
  "idade": 19,
  "nacionalidade": "England",
  "posicaoPrincipal": "MC",
  "posicoesSecundarias": [],
  "pernaDominante": "D",
  "atributos": {
   "finalizacao": 50,
   "passe": 62,
   "marcacao": 59,
   "desarme": 53,
   "velocidade": 53,
   "resistencia": 64,
   "forca": 52,
   "reflexos": 4,
   "posicionamento": 56,
   "drible": 58,
   "cabeceio": 50,
   "cruzamento": 58
  },
  "overall": 56,
  "potencial": 60,
  "condicaoFisica": 100,
  "moral": 70,
  "forma": 0,
  "valorMercado": 70000,
  "salario": 22000,
  "contratoAte": "2028-12-31",
  "clubeId": "club_sheffield_wednesday",
  "lesionado": false,
  "diasLesao": 0,
  "suspenso": false,
  "jogosSuspensao": 0,
  "estatisticasTemporada": {
   "temporada": "2026",
   "jogos": 0,
   "gols": 0,
   "assistencias": 0,
   "cartoesAmarelos": 0,
   "cartoesVermelhos": 0,
   "notaMedia": 0
  },
  "historicoTemporadas": []
 }
]
